composer_mailparser/__init__.py
composer_mailparser/__main__.py
composer_mailparser/composer_mailparser.py
composer_mailparser/const.py
composer_mailparser/exceptions.py
composer_mailparser/utils.py
composer_mailparser/version.py
composer_mailparser-3.9.6.dist-info/LICENSE.txt
composer_mailparser-3.9.6.dist-info/METADATA
composer_mailparser-3.9.6.dist-info/NOTICE.txt
composer_mailparser-3.9.6.dist-info/WHEEL
composer_mailparser-3.9.6.dist-info/entry_points.txt
composer_mailparser-3.9.6.dist-info/top_level.txt
composer_mailparser-3.9.6.dist-info/RECORD
